affinidi/common_check_widget_backend_lib/__init__.py
affinidi/common_check_widget_backend_lib/py.typed
affinidi/common_check_widget_backend_lib/_jsii/__init__.py
affinidi/common_check_widget_backend_lib/_jsii/common-check-widget-backend-lib@2.1.1.jsii.tgz
affinidi/common_check_widget_backend_lib/common_check_verify/__init__.py
affinidi/common_check_widget_backend_lib/common_check_verify/endpoint_service_base/__init__.py
affinidi.common_check_widget_backend_lib-2.1.1.dist-info/LICENSE
affinidi.common_check_widget_backend_lib-2.1.1.dist-info/METADATA
affinidi.common_check_widget_backend_lib-2.1.1.dist-info/WHEEL
affinidi.common_check_widget_backend_lib-2.1.1.dist-info/top_level.txt
affinidi.common_check_widget_backend_lib-2.1.1.dist-info/RECORD
