Metadata-Version: 2.1
Name: affinidi.common-check-widget-backend-lib
Version: 2.1.1
Summary: An common-check-widget-backend-lib used to development backend for common-check-widget-frontend
Home-page: https://gitlab.com/affinidi/safe-travel/st-experiments/common-check-widget-backend-lib
Author: Chai Jian Wei <jianwei.c@affinidi.com>
License: MIT-0
Project-URL: Source, https://github.com/affinityproject/common-check-widget-backend-lib.git
Platform: UNKNOWN
Classifier: Intended Audience :: Developers
Classifier: Operating System :: OS Independent
Classifier: Programming Language :: JavaScript
Classifier: Programming Language :: Python :: 3 :: Only
Classifier: Programming Language :: Python :: 3.6
Classifier: Programming Language :: Python :: 3.7
Classifier: Programming Language :: Python :: 3.8
Classifier: Programming Language :: Python :: 3.9
Classifier: Typing :: Typed
Classifier: License :: OSI Approved
Requires-Python: >=3.6
Requires-Dist: jsii (<2.0.0,>=1.32.0)
Requires-Dist: publication (>=0.0.3)
